torchcuts/__init__.py
torchcuts/_filter.py
torchcuts/_tcuts.py
torchcuts-0.0.4.dist-info/LICENSE
torchcuts-0.0.4.dist-info/METADATA
torchcuts-0.0.4.dist-info/WHEEL
torchcuts-0.0.4.dist-info/top_level.txt
torchcuts-0.0.4.dist-info/RECORD
