Metadata-Version: 2.1
Name: torchcuts
Version: 0.0.4
Summary: Shortcuts to torch
Home-page: https://github.com/AsgerJon
Author: Asger Jon Vistisen
Author-email: asgerjon2@gmail.com
Classifier: Programming Language :: Python :: 3
Classifier: License :: OSI Approved :: MIT License
Classifier: Operating System :: OS Independent
Requires-Python: >=3.7
License-File: LICENSE
